{"_ts":[1575167815,1575185869,1575203938,1575222168,1575240105,1575258030,1575275842,1575293849,1575312142,1575330141,1575348025,1575369114,1575402147,1575420028,1575438084,1575455936],"_r":{"breakdown":{"html":{"bytes":[0,0,0,0,0,0,0,0,0,0,0,0,0,0,0,0],"requests":[0,0,0,0,0,0,0,0,0,0,0,0,0,0,0,0]},"js":{"bytes":[0,0,0,0,0,0,0,0,0,0,0,0,0,0,0,0],"requests":[0,0,0,0,0,0,0,0,0,0,0,0,0,0,0,0]},"css":{"bytes":[0,0,0,0,0,0,0,0,0,0,0,0,0,0,0,0],"requests":[0,0,0,0,0,0,0,0,0,0,0,0,0,0,0,0]},"image":{"bytes":[0,0,0,0,0,0,0,0,0,0,0,0,0,0,0,0],"requests":[0,0,0,0,0,0,0,0,0,0,0,0,0,0,0,0]},"flash":{"bytes":[0,0,0,0,0,0,0,0,0,0,0,0,0,0,0,0],"requests":[0,0,0,0,0,0,0,0,0,0,0,0,0,0,0,0]},"font":{"bytes":[0,0,0,0,0,0,0,0,0,0,0,0,0,0,0,0],"requests":[0,0,0,0,0,0,0,0,0,0,0,0,0,0,0,0]},"video":{"bytes":[0,0,0,0,0,0,0,0,0,0,0,0,0,0,0,0],"requests":[0,0,0,0,0,0,0,0,0,0,0,0,0,0,0,0]},"other":{"bytes":[0,0,0,0,0,0,0,0,0,0,0,0,0,0,0,0],"requests":[0,0,0,0,0,0,0,0,0,0,0,0,0,0,0,0]}},"date":[1575167815,1575185869,1575203938,1575222168,1575240105,1575258030,1575275842,1575293849,1575312142,1575330141,1575348025,1575369114,1575402147,1575420028,1575438084,1575455936],"domElements":[null,null,null,null,null,null,null,null,null,null,null,null,null,null,null,null],"domInteractive":[null,null,null,null,null,null,null,null,null,null,null,null,null,null,null,null],"firstPaint":[null,null,null,null,null,null,null,null,null,null,null,null,null,null,null,null],"fullyLoaded":[null,null,null,null,null,null,null,null,null,null,null,null,null,null,null,null],"id":["191201_84_1eed6a5ad525f08e724ca99a98287895","191201_M3_71913021dbe8ebd0e8486e3e30ed6d4b","191201_WK_d59ad5900a075b9f0b03cd9b508219f7","191201_QN_7064e0cd92b8f956ac623a4c87af0c86","191201_SC_23f784a6b45c8a006b97a88732f86132","191202_BG_bc044ad9714957bbe3234983c18449c5","191202_8V_aeebe132ad839933feff72c018577584","191202_W7_f07b9222c5d4a54f7f6022403de20799","191202_4R_7070cf477537bafa9261a17eacd57438","191202_DY_fa9063ebe231b575ab4c19fae90421d4","191203_EJ_ae90590bad876a8260ace861f0b6dc39","191203_JR_183cea5d457a5cdb195f291c9eb670bd","191203_RA_b56af913ebb79ced49b9d5d212c56aca","191204_XX_1fd7e379c61160fa68e101b940e40919","191204_Y5_ad1bf4eac8b6e1efd6a5bd3050843361","191204_GY_c172fb1bde27b9811057f283b86fd963"],"loadTime":[null,null,null,null,null,null,null,null,null,null,null,null,null,null,null,null],"render":[null,null,null,null,null,null,null,null,null,null,null,null,null,null,null,null],"SpeedIndex":[null,null,null,null,null,null,null,null,null,null,null,null,null,null,null,null],"TTFB":[null,null,null,null,null,null,null,null,null,null,null,null,null,null,null,null],"videoFrames":[[{"_i":"ms_000000.jpg","_t":0,"_vc":100}],[{"_i":"ms_000000.jpg","_t":0,"_vc":100}],[{"_i":"ms_000000.jpg","_t":0,"_vc":100}],[{"_i":"ms_000000.jpg","_t":0,"_vc":100}],[{"_i":"ms_000000.jpg","_t":0,"_vc":100}],[{"_i":"ms_000000.jpg","_t":0,"_vc":100}],[{"_i":"ms_000000.jpg","_t":0,"_vc":100}],[{"_i":"ms_000000.jpg","_t":0,"_vc":100}],[{"_i":"ms_000000.jpg","_t":0,"_vc":100}],[{"_i":"ms_000000.jpg","_t":0,"_vc":100}],[{"_i":"ms_000000.jpg","_t":0,"_vc":100}],[{"_i":"ms_000000.jpg","_t":0,"_vc":100}],[{"_i":"ms_000000.jpg","_t":0,"_vc":0},{"_i":"ms_000200.jpg","_t":200,"_vc":100}],[{"_i":"ms_000000.jpg","_t":0,"_vc":100}],[{"_i":"ms_000000.jpg","_t":0,"_vc":100}],[{"_i":"ms_000000.jpg","_t":0,"_vc":100}]],"visualComplete":[null,null,null,null,null,null,null,null,null,null,null,null,null,null,null,null],"lighthouse":[null,null,null,null,null,null,null,null,null,null,null,null,null,null,null,null],"pagespeed":[null,null,null,null,null,null,null,null,null,null,null,null,null,null,null,null]}}